clubwarrior/__init__.py
clubwarrior/clubhouse.py
clubwarrior/clubwarrior.py
clubwarrior/config.py
clubwarrior-0.0.4.dist-info/DESCRIPTION.rst
clubwarrior-0.0.4.dist-info/METADATA
clubwarrior-0.0.4.dist-info/RECORD
clubwarrior-0.0.4.dist-info/WHEEL
clubwarrior-0.0.4.dist-info/entry_points.txt
clubwarrior-0.0.4.dist-info/metadata.json
clubwarrior-0.0.4.dist-info/top_level.txt
