Metadata-Version: 2.0
Name: clubwarrior
Version: 0.0.4
Summary: Track and sync your Clubhouse.io stories in TaskWarrior
Home-page: https://github.com/huntrar/clubwarrior
Author: Hunter Hammond
Author-email: clubwarrior.dev@gmail.com
License: MIT
Keywords: clubhouse.io taskwarrior task tracking management sync
Platform: UNKNOWN
Classifier: License :: OSI Approved :: MIT License
Classifier: Programming Language :: Python :: 3
Requires-Dist: requests
Requires-Dist: tasklib
